date_time_literal/__init__.py
date_time_literal/difference.py
date_time_literal/literal.py
date_time_literal/main.py
date_time_literal-1.1.0.dist-info/LICENSE
date_time_literal-1.1.0.dist-info/METADATA
date_time_literal-1.1.0.dist-info/WHEEL
date_time_literal-1.1.0.dist-info/top_level.txt
date_time_literal-1.1.0.dist-info/RECORD
